nose_launchable/__init__.py
nose_launchable/case_event.py
nose_launchable/client.py
nose_launchable/log.py
nose_launchable/manager.py
nose_launchable/plugin.py
nose_launchable/protecter.py
nose_launchable/test_path_component.py
nose_launchable/uploader.py
nose_launchable/version.py
tests/__init__.py
tests/test_client.py
tests/test_manager.py
tests/test_protecter.py
tests/test_uploader.py
tests/resources/__init__.py
tests/resources/module0.py
tests/resources/module1.py
tests/resources/module2.py
nose_launchable-0.6.0.dist-info/LICENSE
nose_launchable-0.6.0.dist-info/METADATA
nose_launchable-0.6.0.dist-info/WHEEL
nose_launchable-0.6.0.dist-info/entry_points.txt
nose_launchable-0.6.0.dist-info/top_level.txt
nose_launchable-0.6.0.dist-info/RECORD
