Metadata-Version: 2.1
Name: nose-launchable
Version: 0.6.0
Summary: A nose plugin to interact with Launchable API
Home-page: https://github.com/launchableinc/nose-launchable
Author: Launchable team
Author-email: info@launchableinc.com
Classifier: Development Status :: 3 - Alpha
Classifier: Intended Audience :: Developers
Classifier: License :: OSI Approved :: Apache Software License
Classifier: Programming Language :: Python :: 3
License-File: LICENSE
Requires-Dist: launchable >=1.26.0,~=1.0
Requires-Dist: boto3 >=1.0.0
Requires-Dist: requests >=2.0.0
Requires-Dist: urllib3 <2
Requires-Dist: nose >=1.0.0 ; python_version < "3.10"
Requires-Dist: pynose >=1.5.1 ; python_version >= "3.10"
